deadline/rhino_submitter/__init__.py
deadline/rhino_submitter/__main__.py
deadline/rhino_submitter/_version.py
deadline/rhino_submitter/data_classes.py
deadline/rhino_submitter/default_rhino_job_template.yaml
deadline/rhino_submitter/rhino_render_submitter.py
deadline/rhino_submitter/ui/__init__.py
deadline/rhino_submitter/ui/components/__init__.py
deadline/rhino_submitter/ui/components/scene_settings_tab.py
deadline_cloud_for_rhino-0.1.4.dist-info/METADATA
deadline_cloud_for_rhino-0.1.4.dist-info/WHEEL
deadline_cloud_for_rhino-0.1.4.dist-info/licenses/LICENSE
deadline_cloud_for_rhino-0.1.4.dist-info/licenses/NOTICE
deadline_cloud_for_rhino-0.1.4.dist-info/RECORD
