Metadata-Version: 2.3
Name: deadline-cloud-for-rhino
Version: 0.1.4
Summary: AWS Deadline Cloud for Rhino
Project-URL: Homepage, https://github.com/aws-deadline/deadline-cloud-for-rhino
Project-URL: Source, https://github.com/aws-deadline/deadline-cloud-for-rhino
Author: Amazon Web Services
License: Apache-2.0
Classifier: Development Status :: 3 - Alpha
Classifier: Intended Audience :: Developers
Classifier: Intended Audience :: End Users/Desktop
Classifier: License :: OSI Approved :: Apache Software License
Classifier: Operating System :: MacOS
Classifier: Operating System :: Microsoft :: Windows
Classifier: Programming Language :: Python
Classifier: Programming Language :: Python :: 3 :: Only
Classifier: Programming Language :: Python :: 3.9
Classifier: Programming Language :: Python :: 3.10
Classifier: Programming Language :: Python :: 3.11
Classifier: Programming Language :: Python :: 3.12
Requires-Python: >=3.9
Requires-Dist: deadline==0.49.*
